LICENSE.txt
MANIFEST.in
README.md
setup.py
.eggs/README.txt
.eggs/setuptools_git-1.2-py2.7.egg
vaksana/__init__.py
vaksana/sdk.py
vaksana/interceptors/__init__.py
vaksana/interceptors/consumer_interceptor.py
vaksana/interceptors/producer_interceptor.py
vaksana/test/test.cfg
vaksana/test/test.pem
vaksana/test/test.py
vaksana/test/sdk_config/ca.cert
vaksana/test/sdk_config/docker.cert
vaksana/test/sdk_config/docker.pem
vaksana/utils/__init__.py
vaksana/utils/encrypt.py
vaksana_sdk.egg-info/PKG-INFO
vaksana_sdk.egg-info/SOURCES.txt
vaksana_sdk.egg-info/dependency_links.txt
vaksana_sdk.egg-info/requires.txt
vaksana_sdk.egg-info/top_level.txt