Metadata-Version: 1.0
Name: vaksana-sdk
Version: 0.6.5.dev0
Summary: SDK to connect to Vaksana Marketplace
Home-page: http://vaksana.com/sdk#python
Author: Pankaj Garg
Author-email: garg.pankaj83@gmail.com
License: PSF
Keywords: Vaksana
Platform: UNKNOWN
